hymaia_cli/__init__.py
hymaia_cli/command/__init__.py
hymaia_cli/command/command.py
hymaia_cli/command/hymaia_cli_commands.py
hymaia_cli/main.py
hymaia_cli/resources/config.ini
hymaia_cli/utils/__init__.py
hymaia_cli/utils/custom_argparse.py
hymaia_cli/utils/printing.py
hymaia_cli-1.0.1.dist-info/entry_points.txt
hymaia_cli-1.0.1.dist-info/WHEEL
hymaia_cli-1.0.1.dist-info/METADATA
hymaia_cli-1.0.1.dist-info/RECORD
