Metadata-Version: 2.1
Name: hymaia-cli
Version: 1.0.1
Summary: 
Author: Elhadi Cherifi
Author-email: elhadi.cherifi@hymaia.com
Requires-Python: >=3.9,<4.0
Classifier: Programming Language :: Python :: 3
Classifier: Programming Language :: Python :: 3.10
Classifier: Programming Language :: Python :: 3.9
Requires-Dist: requests (>=2.27.1,<3.0.0)
